ai_factory_model/__init__.py
ai_factory_model/config/__init__.py
ai_factory_model/config/config.py
ai_factory_model/llm/__init__.py
ai_factory_model/llm/factory.py
ai_factory_model/llm/model_AzureAIChat.py
ai_factory_model/llm/model_AzureOpenAIChat.py
ai_factory_model/llm/model_AzureOpenAIEmbedding.py
ai_factory_model/llm/model_GoogleAIChat.py
ai_factory_model/llm/model_GoogleAIEmbedding.py
ai_factory_model/llm/model_HFEmbedding.py
ai_factory_model/llm/model_LMEmbedding.py
ai_factory_model/llm/model_LMStudioChat.py
ai_factory_model/llm/model_OllamaChat.py
ai_factory_model/llm/model_OpenAIChat.py
ai_factory_model/llm/model_OpenAIEmbedding.py
ai_factory_model/llm/model_base.py
ai_factory_model/llm/model_base_embedding.py
ai_factory_model/llm/model_utils.py
ai_factory_model/llm/auth_clients/__init__.py
ai_factory_model/llm/auth_clients/azure.py
ai_factory_model/logger/__init__.py
ai_factory_model/logger/logger.py
ai_factory_model/logger/logger_config.py
ai_factory_model/logger/utils.py
ai_factory_model/security/__init__.py
ai_factory_model/security/keyvault_handler.py
ai_factory_model/vectordb/__init__.py
ai_factory_model/vectordb/factory.py
ai_factory_model/vectordb/vectordb_AISearch.py
ai_factory_model/vectordb/vectordb_PGVector.py
ai_factory_model/vectordb/vectordb_base.py
ai_factory_model/vectordb/vectordb_utils.py
ai_factory_model-0.0.7.dist-info/METADATA
ai_factory_model-0.0.7.dist-info/WHEEL
ai_factory_model-0.0.7.dist-info/top_level.txt
ai_factory_model-0.0.7.dist-info/RECORD
