Metadata-Version: 2.4
Name: ai_factory_model
Version: 0.0.7
Summary: AI Library to authenticate and manage LLM models
License-Expression: MIT
Classifier: Environment :: Web Environment
Classifier: Framework :: Flask
Classifier: Intended Audience :: Developers
Classifier: Programming Language :: Python :: 3
Classifier: Programming Language :: Python :: 3 :: Only
Classifier: Programming Language :: Python :: 3.12
Classifier: Programming Language :: Python :: 3.13
Classifier: Operating System :: OS Independent
Classifier: Topic :: Software Development :: Libraries :: Python Modules
Requires-Python: >=3.12
Requires-Dist: openai>=1.72.0
Requires-Dist: azure-core>=1.33.0
Requires-Dist: azure-identity>=1.21.0
Requires-Dist: azure-keyvault-secrets>=4.9.0
Requires-Dist: langchain>=0.3.23
Requires-Dist: langchain_openai>=0.3.12
Requires-Dist: langchain_azure_ai>=0.1.2; python_version < "3.13"
Requires-Dist: langchain_google_genai>=2.1.2
Requires-Dist: langchain_community>=0.3.21
Requires-Dist: langchain_ollama>=0.3.1
Requires-Dist: jinja2>=3.1.6
Requires-Dist: python-decouple>=3.8
Requires-Dist: pyyaml>=6.0.2
Requires-Dist: azure-search-documents==11.5.2
Requires-Dist: psycopg[binary]==3.2.6
Requires-Dist: langchain-cohere==0.4.3
